testproject/__init__.py
testproject/manage.py
testproject/testapp/__init__.py
testproject/testapp/apps.py
testproject/testapp/models.py
testproject/testapp/migrations/0001_initial.py
testproject/testapp/migrations/0002_contactpage.py
testproject/testapp/migrations/__init__.py
testproject/testproject/__init__.py
testproject/testproject/settings.py
testproject/testproject/urls.py
testproject/testproject/wsgi.py
wagtail_extensions/__init__.py
wagtail_extensions/admin.py
wagtail_extensions/app_settings.py
wagtail_extensions/blocks.py
wagtail_extensions/forms.py
wagtail_extensions/mixins.py
wagtail_extensions/models.py
wagtail_extensions/utils.py
wagtail_extensions/migrations/0001_initial.py
wagtail_extensions/migrations/0002_alter_contactsubmission_data.py
wagtail_extensions/migrations/__init__.py
wagtail_extensions/static/wagtail_extensions/js/maps.js
wagtail_extensions/static/wagtail_extensions/scss/components/carousel.scss
wagtail_extensions/static/wagtail_extensions/scss/components/images.scss
wagtail_extensions/templates/wagtail_extensions/blocks/address.html
wagtail_extensions/templates/wagtail_extensions/blocks/carousel.html
wagtail_extensions/templates/wagtail_extensions/blocks/carousel_item.html
wagtail_extensions/templates/wagtail_extensions/blocks/images.html
wagtail_extensions/templates/wagtail_extensions/blocks/link.html
wagtail_extensions/templates/wagtail_extensions/blocks/opening_time.html
wagtail_extensions/templates/wagtail_extensions/blocks/opening_times.html
wagtail_extensions/templates/wagtail_extensions/blocks/social_media_profile.html
wagtail_extensions/templates/wagtail_extensions/blocks/text.html
wagtail_extensions/templates/wagtail_extensions/email/message.txt
wagtail_extensions/templates/wagtail_extensions/email/subject.txt
wagtail_extensions/templates/wagtail_extensions/partials/map.html
wagtail_extensions/templates/wagtail_extensions/partials/map_assets.html
wagtail_extensions/templates/wagtail_extensions/partials/menu.html
regulus_wagtail_extensions-2.7.0.dist-info/LICENSE
regulus_wagtail_extensions-2.7.0.dist-info/METADATA
regulus_wagtail_extensions-2.7.0.dist-info/WHEEL
regulus_wagtail_extensions-2.7.0.dist-info/top_level.txt
regulus_wagtail_extensions-2.7.0.dist-info/RECORD
