Metadata-Version: 2.1
Name: regulus-wagtail-extensions
Version: 2.7.0
Summary: A few useful extensions for Wagtail
Home-page: https://github.com/regulusweb/wagtail-extensions
Author: Regulus Ltd
Author-email: reg@regulusweb.com
License: MIT License
Platform: UNKNOWN
Classifier: Environment :: Web Environment
Classifier: Framework :: Django
Classifier: Framework :: Django :: 3.1
Classifier: Framework :: Django :: 3.2
Classifier: Intended Audience :: Developers
Classifier: License :: OSI Approved :: MIT License
Classifier: Operating System :: OS Independent
Classifier: Programming Language :: Python
Classifier: Programming Language :: Python :: 3
Classifier: Programming Language :: Python :: 3.7
Classifier: Programming Language :: Python :: 3.8
Classifier: Programming Language :: Python :: 3.9
Classifier: Topic :: Internet :: WWW/HTTP
Classifier: Topic :: Internet :: WWW/HTTP :: Dynamic Content
Requires-Python: >=3.7
Requires-Dist: wagtail (<3,>=2.11)
Requires-Dist: django-phonenumber-field
Requires-Dist: phonenumbers
Requires-Dist: python-dateutil
Requires-Dist: wagtailgeowidget
Requires-Dist: django-recaptcha (<3.1,>=3.0)
Requires-Dist: django-crispy-forms (>=1.12)
Requires-Dist: bleach (>=2.0.0)
Provides-Extra: test
Requires-Dist: freezegun (<1.2,>=0.3) ; extra == 'test'
Requires-Dist: pytest-django (<4.5,>=4.4) ; extra == 'test'
Requires-Dist: pytest-xdist (<2.5,>=2.3) ; extra == 'test'
Requires-Dist: psycopg2-binary ; extra == 'test'
